coveredebug/__init__.py
coveredebug/cli.py
coveredebug-0.0.9.1.dist-info/AUTHORS.rst
coveredebug-0.0.9.1.dist-info/LICENSE.txt
coveredebug-0.0.9.1.dist-info/METADATA
coveredebug-0.0.9.1.dist-info/WHEEL
coveredebug-0.0.9.1.dist-info/entry_points.txt
coveredebug-0.0.9.1.dist-info/top_level.txt
coveredebug-0.0.9.1.dist-info/RECORD
